interstellar/__init__.py
interstellar/__main__.py
interstellar/cli.py
interstellar/tools.py
interstellar-1.1.5.dist-info/licenses/LICENSE
interstellar-1.1.5.dist-info/METADATA
interstellar-1.1.5.dist-info/WHEEL
interstellar-1.1.5.dist-info/entry_points.txt
interstellar-1.1.5.dist-info/top_level.txt
interstellar-1.1.5.dist-info/RECORD
