Metadata-Version: 2.4
Name: interstellar
Version: 1.1.5
Summary: A command-line tool for managing cryptocurrency mnemonics using BIP39 and SLIP39 standards
Author: interstellar contributors
License-Expression: MIT
Project-URL: Homepage, https://github.com/alkalescent/interstellar
Project-URL: Repository, https://github.com/alkalescent/interstellar
Project-URL: Issues, https://github.com/alkalescent/interstellar/issues
Keywords: cryptocurrency,mnemonic,bip39,slip39,shamir,hdwallet
Classifier: Development Status :: 3 - Alpha
Classifier: Intended Audience :: Developers
Classifier: Topic :: Security :: Cryptography
Classifier: Programming Language :: Python :: 3
Classifier: Programming Language :: Python :: 3.13
Requires-Python: >=3.13
License-File: LICENSE
Requires-Dist: mnemonic>=0.21
Requires-Dist: slip39>=14.0.2
Requires-Dist: typer>=0.20.1
Dynamic: license-file
